[
    {
        "题号": "1",
        "题目": "（）给中国送来了马克思列宁主义，给苦苦探寻救亡图存出路的中国人民指明了前进方向、提供了全新选择。",
        "选项": [
            "鸦片战争",
            "新文化运动",
            "五四运动",
            "十月革命"
        ],
        "难度": "中",
        "题型": "单选题",
        "正确答案": "D",
        "解析": ""
    },
    {
        "题号": "2",
        "题目": "1938年，（）在党的六届六中全会上作了《论新阶段》的报告，强调：“没有抽象的马克思主义，只有具体的马克思主义……”",
        "选项": [
            "毛泽东",
            "任弼时",
            "刘少奇",
            "周恩来"
        ],
        "难度": "中",
        "题型": "单选题",
        "正确答案": "A",
        "解析": ""
    },
    {
        "题号": "3",
        "题目": "党的十八大以来，以习近平同志为核心的党中央明确提出要不断推进（）。",
        "选项": [
            "社会主义现代化",
            "马克思主义中国化时代化",
            "“两个结合”",
            "社会主义现代化强国"
        ],
        "难度": "中",
        "题型": "单选题",
        "正确答案": "B",
        "解析": ""
    },
    {
        "题号": "4",
        "题目": "（ ）明确把“不断谱写马克思主义中国化时代化新篇章”作为当代中国共产党人的庄严历史责任，并提出了继续推进马克思主义中国化时代化的新要求。",
        "选项": [
            "党的十七大",
            "党的十八大",
            "党的十九大",
            "党的二十大"
        ],
        "难度": "中",
        "题型": "单选题",
        "正确答案": "D",
        "解析": ""
    },
    {
        "题号": "5",
        "题目": "（）是马克思主义中国化时代化的第一次历史性飞跃。",
        "选项": [
            "毛泽东思想",
            "邓小平理论",
            "“三个代表”重要思想",
            "科学发展观"
        ],
        "难度": "中",
        "题型": "单选题",
        "正确答案": "A",
        "解析": ""
    },
    {
        "题号": "6",
        "题目": "马克思主义中国化时代化的理论成果是一脉相承又（）的关系。",
        "选项": [
            "实事求是",
            "与时俱进",
            "独立自主",
            "精益求精"
        ],
        "难度": "中",
        "题型": "单选题",
        "正确答案": "B",
        "解析": ""
    },
    {
        "题号": "7",
        "题目": "马克思主义中国化时代化的最新理论成果是（）。",
        "选项": [
            "毛泽东思想",
            "科学发展观",
            "习近平新时代中国特色社会主义思想",
            "邓小平理论"
        ],
        "难度": "中",
        "题型": "单选题",
        "正确答案": "C",
        "解析": ""
    },
    {
        "题号": "8",
        "题目": "（）的召开，实现了新中国成立以来党的历史上具有深远意义的伟大转折，开启了改革开放和社会主义现代化建设历史新时期。",
        "选项": [
            "中共十一届三中全会",
            "中共十二大",
            "中共十三大",
            "中共十一届六中全会"
        ],
        "难度": "中",
        "题型": "单选题",
        "正确答案": "A",
        "解析": ""
    },
    {
        "题号": "9",
        "题目": "中国特色社会主义理论体系不包括（）。",
        "选项": [
            "邓小平理论",
            "科学发展观",
            "习近平新时代中国特色社会主义思想",
            "毛泽东思想"
        ],
        "难度": "中",
        "题型": "单选题",
        "正确答案": "D",
        "解析": ""
    },
    {
        "题号": "10",
        "题目": "中国共产党一经诞生，就把为中国人民谋幸福、为中华民族谋复兴确立为自己的初心使命。一百年来，中国共产党团结带领中国人民进行的一切奋斗、一切牺牲、一切创造，归结起来就是一个主题（ ）。",
        "选项": [
            "实现共同富裕",
            "实现全面建成小康社会",
            "实现社会主义现代化",
            "实现中华民族伟大复兴"
        ],
        "难度": "中",
        "题型": "单选题",
        "正确答案": "D",
        "解析": ""
    },
    {
        "题号": "11",
        "题目": "准确把握马克思主义中国化时代化的科学内涵，要做到坚持（）与（）相统一。",
        "选项": [
            "马克思主义",
            "发展马克思主义",
            "社会主义",
            "中国特色社会主义"
        ],
        "难度": "难",
        "题型": "多选题",
        "正确答案": "A.B.",
        "解析": ""
    },
    {
        "题号": "12",
        "题目": "推进马克思主义中国化时代化，是（ ）。",
        "选项": [
            "马克思主义唯物史观的要求",
            "马克思主义理论本身发展的内在要求",
            "解决中国实际问题的客观需要",
            "社会主义经济社会发展的需要"
        ],
        "难度": "难",
        "题型": "多选题",
        "正确答案": "B.C.",
        "解析": ""
    },
    {
        "题号": "13",
        "题目": "坚持和发展马克思主义，必须（）。",
        "选项": [
            "同中国具体实际相结合",
            "同中华优秀传统文化相结合",
            "同社会主义现代化发展相结合",
            "同中华民族伟大复兴相结合"
        ],
        "难度": "难",
        "题型": "多选题",
        "正确答案": "A.B.",
        "解析": ""
    },
    {
        "题号": "14",
        "题目": "要坚持解放思想、实事求是、与时俱进、求真务实，一切从实际出发，着眼解决革命、建设、改革中的实际问题，不断回答（），作出符合中国实际和时代要求的正确回答，得出符合客观规律的科学认识，形成与时俱进的理论成果，更好指导中国实践。",
        "选项": [
            "中国之问",
            "世界之问",
            "人民之问",
            "时代之问"
        ],
        "难度": "难",
        "题型": "多选题",
        "正确答案": "A.B.C.D.",
        "解析": ""
    },
    {
        "题号": "15",
        "题目": "实践证明，中国共产党为什么能，中国特色社会主义为什么好，归根到底是（）。",
        "选项": [
            "马克思主义经典作家行",
            "科学社会主义行",
            "马克思主义行",
            "中国化时代化的马克思主义行"
        ],
        "难度": "难",
        "题型": "多选题",
        "正确答案": "C.D.",
        "解析": ""
    },
    {
        "题号": "16",
        "题目": "马克思主义中国化时代化的内涵是（）",
        "选项": [
            "就是立足中国国情和时代特点",
            "坚持把马克思主义基本原理同中国具体实际相结合、同中华优秀传统文化相结合，",
            "深入研究和解决中国革命、建设、改革不同历史时期的实际问题",
            "真正搞懂面临的时代课题，不断吸收新的时代内容，科学回答时代提出的重大理论和实践课题，创造新的理论成果。"
        ],
        "难度": "难",
        "题型": "多选题",
        "正确答案": "A.B.C.D.",
        "解析": ""
    },
    {
        "题号": "17",
        "题目": "在中国共产党历史上，最早提出“马克思主义中国化”这个命题的是",
        "选项": [
            "李大钊",
            "陈独秀",
            "毛泽东",
            "张闻天"
        ],
        "难度": "难",
        "题型": "单选题",
        "正确答案": "C",
        "解析": "解析：1938年，毛泽东在党的六届六中全会强调：“马克思主义的中国化，使之在其每一表现中带着中国的特性”标志着“马克思主义中国化”这一命题正式提出"
    },
    {
        "题号": "18",
        "题目": "新民主主义革命理论是毛泽东思想的重要组成部分。下列关于新民主主义革命的认识，不正确的是（）。",
        "选项": [
            "它是毛泽东思想初步形成的主要标志",
            "它是具有独创性的关于中国人民革命的理论",
            "它是马克思主义中国化的重要理论成果",
            "它是反映中国新民主主义革命客观规律的完备理论"
        ],
        "难度": "中",
        "题型": "单选题",
        "正确答案": "A",
        "解析": "“农村包围城市、武装夺取政权”理论的提出，标志着毛泽东思想的初步形成。新民主主义理论的提出标志着毛泽东思想的全面成熟。"
    },
    {
        "题号": "19",
        "题目": "毛泽东在下列哪篇文章中提出了“没有调查，就没有发言权”的著名论断",
        "选项": [
            "《湖南农民运动考察报告》",
            "《井冈山的斗争》",
            "《反对本本主义》",
            "《实践论》"
        ],
        "难度": "易",
        "题型": "单选题",
        "正确答案": "C",
        "解析": "解析：C写于1931年5月，标志着实事求是思想路线的基本形成。A是毛泽东形成新民主主义革命基本思想过程中的一篇文章。B是毛泽东形成农村包围城市道路理论过程中的一篇重要文章。D是1937年写的，为实事求是思想路线奠定了理论基础。"
    },
    {
        "题号": "20",
        "题目": "在下列著作中，毛泽东把教条主义者比喻为“墙上芦苇，头重脚轻根底浅；山间竹笋嘴尖皮厚腹中空”的是",
        "选项": [
            "《改造我们的学习》",
            "《整顿党的作风》",
            "《反对本本主义》",
            "《为人民服务》"
        ],
        "难度": "中",
        "题型": "单选题",
        "正确答案": "A",
        "解析": "解析：《改造我们的学习》一文是毛泽东关于整风运动的著作，这篇文章第一次提出了“马克思列宁主义的普遍真理和中国革命的具体实践相结合”这一表述；并在这篇文章中把教条主义者比喻为“墙上芦苇，头重脚轻根底浅；山间竹笋，嘴尖皮厚腹中空”。因此A为本题正确选项。B项《整顿党的作风》；C项《反对本本主义》；D项《为人民服务》均不符合本题要求，应排除"
    },
    {
        "题号": "21",
        "题目": "下列哪一项不是毛泽东总结的中国共产党人区别于其他任何政党的显著标志",
        "选项": [
            "理论和实践相结合的作风",
            "和人民群众紧密地联系在一起的作风",
            "自我批评的作风",
            "统一战线的作风"
        ],
        "难度": "中",
        "题型": "单选题",
        "正确答案": "D",
        "解析": ""
    },
    {
        "题号": "22",
        "题目": "中国共产党的根本宗旨和一切工作的根本出发点是",
        "选项": [
            "全心全意为人民服务",
            "实事求是",
            "批评与自我批评",
            "理论联系实际"
        ],
        "难度": "难",
        "题型": "单选题",
        "正确答案": "A",
        "解析": "［解析］教材30页：坚持群众路线 ，就要坚持全心全意为人民服务的根本宗旨 。全心全意为人民服务，是我们党一切行动的根本出发点和落脚点，是我们党区别于其他一切政党的根本标志 。"
    },
    {
        "题号": "23",
        "题目": "下列哪项不是毛泽东思想的主要内容？",
        "选项": [
            "社会主义市场经济理论",
            "新民主主义革命理论",
            "社会主义革命和建设的理论",
            "政策和策略的理论"
        ],
        "难度": "难",
        "题型": "单选题",
        "正确答案": "A",
        "解析": "［解析］1981年历史决议指出，毛泽东思想的主要内容包括：新民主主义革命理论、社会主义革命和建设的理论、革命军队建设和军事战略的理论、政策和策略的理论、思想政治工作和文化工作的理论、党的建设理论。"
    },
    {
        "题号": "24",
        "题目": "下列选项哪个不是毛泽东思想的活的灵魂？",
        "选项": [
            "独立自主",
            "实事求是",
            "群众路线",
            "调查研究"
        ],
        "难度": "难",
        "题型": "单选题",
        "正确答案": "D",
        "解析": "［解析］1981年党的历史决议指出：贯穿于毛泽东思想各个组成部分的立场、观点和方法，是毛泽东思想的活的灵魂，它们有三个方面，即实事求是，群众路线，独立自主。"
    },
    {
        "题号": "25",
        "题目": "新民主主义革命道路指的是（ ）",
        "选项": [
            "十月革命式的城市暴动",
            "游击战和有利条件下的运动战",
            "改良主义的议会选举",
            "农村包围城市，武装夺取政权"
        ],
        "难度": "难",
        "题型": "单选题",
        "正确答案": "D",
        "解析": "［解析］1927年大革命失败后党的工作重心逐渐转向农村。毛泽东在井冈山革命根据地提出“工农武装割据”思想，初步形成农村包围城市的革命道路理论。长征后，毛泽东进一步论述中国革命的特点，确立了具有中国特点的革命道路。"
    },
    {
        "题号": "26",
        "题目": "建国初年我国用（ ）的方法改造资本主义工商业。",
        "选项": [
            "四马分肥",
            "暴力剥夺",
            "和平赎买",
            "加工订货"
        ],
        "难度": "中",
        "题型": "单选题",
        "正确答案": "C",
        "解析": "［解析］教材72页 中共根据马克思、恩格斯和列宁关于采取和平方式改变所有制的设想，结合中国的具体情况，提出了对资本主义工商业实行和平赎买的方针。所谓赎买，就是国家有偿地将私营企业改变为国营企业，将资本主义私有制改变为社会主义公有制。书买的具体方式不是由国家支付一笔巨额补偿资金，而是让资本家在一定年限内从企业经营中获取一部分利润。"
    },
    {
        "题号": "27",
        "题目": "下列哪项不是我国社会主义改造的历史经验？",
        "选项": [
            "坚持社会主义工业化建设与社会主义改造同时并举",
            "用和平方法进行改造",
            "采取积极引导、逐步过渡的方式",
            "暴力剥夺、行政强制的方式"
        ],
        "难度": "中",
        "题型": "单选题",
        "正确答案": "D",
        "解析": ""
    },
    {
        "题号": "28",
        "题目": "（）标志着党探索中国社会主义建设道路的良好开端？",
        "选项": [
            "《论十大关系》",
            "《关于正确处理人民内部矛盾的问题》",
            "《关于国家资本主义经济》",
            "《新民主主义论》"
        ],
        "难度": "中",
        "题型": "单选题",
        "正确答案": "A",
        "解析": "［解析］毛泽东《论十大关系》初步总结了我国社会主义建设的经验，明确提出要以苏为鉴，独立自主地探索适合中国情况的社会主义道路；明确了建设社会主义必须根据本国国情走自己的路这一根本思想。"
    },
    {
        "题号": "29",
        "题目": "毛泽东认为对于人民内部矛盾的正确处理方法是（ ）",
        "选项": [
            "说服",
            "专政",
            "镇压",
            "整风"
        ],
        "难度": "中",
        "题型": "单选题",
        "正确答案": "A",
        "解析": "［解析］毛泽东提出，敌我矛盾和人民内部矛盾是两类不同性质的矛盾，解决的方法也不同，要分别采用专政和民主两种方法。所谓民主的方法就是讨论的方法，批评的方法，说服教育的方法。"
    },
    {
        "题号": "30",
        "题目": "下列哪项不是毛泽东等第一代领导人提出的中国工业化思想？",
        "选项": [
            "以农业为基础，以工业为主导",
            "为实现“四化”而实行“两步走”的发展战略",
            "在综合平衡中稳步前进的方针",
            "深化要素市场化改革"
        ],
        "难度": "中",
        "题型": "单选题",
        "正确答案": "D",
        "解析": "［解析］深化要素市场化改革是改革开放时期的产物。建国初期受意识形态影响，强调的是公有制，总体排斥私有制，更不要说要素市场化改革了。"
    },
    {
        "题号": "31",
        "题目": "下列哪项不是毛泽东提出的“两参一改三结合”的内容？",
        "选项": [
            "职工代表大会制度",
            "干部参加劳动，工人参加管理",
            "改革不合理的规章制度",
            "工人群众、领导干部和技术人员三结合"
        ],
        "难度": "难",
        "题型": "单选题",
        "正确答案": "A",
        "解析": "［解析］毛泽东提出“鞍钢宪法”，即企业要实行民主管理，实行干部参加劳动，工人参加管理，改革不合理的规章制度，工人群众、领导干部和技术人员三结合。职工代表大会制度是邓小平提出的一项改革内容。"
    },
    {
        "题号": "32",
        "题目": "党的八大确立的社会主要矛盾是（）",
        "选项": [
            "资产阶级和工人阶级之间的矛盾",
            "地主阶级和农民阶级之间的矛盾",
            "人民日益增长的美好生活需要和不平衡不充分的发展之间的矛盾",
            "人民对于建立先进的工业国的要求同落后的农业国的现实之间的矛盾"
        ],
        "难度": "难",
        "题型": "单选题",
        "正确答案": "D",
        "解析": "［解析］党的八大指出，社会主义制度在我国已经基本上建立起来了。我国国内的主要矛盾，已经是人民对于建立先进的工业国的要求同落后的农业国的现实之间的矛盾，已经是人民对于经济文化迅速发展的需要同当前经济文化不能满足人民需要的状况之间的矛盾。"
    },
    {
        "题号": "33",
        "题目": "1939年和1940年，毛泽东完整地提出新民主主义革命的理论，标志毛泽东思想发展和成熟的主要文献是：",
        "选项": [
            "《＜共产党人＞发刊词》",
            "《论人民民主专政》",
            "《新民主主义论》",
            "《中国革命和中国共产党》"
        ],
        "难度": "中",
        "题型": "多选题",
        "正确答案": "A.C.D.",
        "解析": "[命题分析]本题考查的知识点是：1939年和1940年，标志毛泽东思想发展和成熟的主要文献。在毛泽东思想的成熟期，毛泽东进行了大量的创造性的理论研究工作，撰写了大量着名的文章和着作，系统总结了中国革命丰富的正反两方面经验，科学揭示了中国革命的特殊规律。其中写于1939年和1940年的文章包括《＜共产党人＞发刊词》、《中国革命和中国共产党》、《新民主主义论》。《论人民民主专政》写于1949年。因此，本题的正确答案是ACD选项。"
    },
    {
        "题号": "34",
        "题目": "在土地革命前期，毛泽东撰写了形成农村包围城市道路理论的着名着作有：",
        "选项": [
            "《中国的红色政权为什么能够存在》",
            "《星星之火，可以燎原》",
            "《井冈山的斗争》",
            "《反对本本主义》"
        ],
        "难度": "中",
        "题型": "多选题",
        "正确答案": "A.B.C.D.",
        "解析": "[命题分析]本题考查的知识点是：毛泽东在土地革命前期的着名着作。土地革命前期指的是1927年大革命失败后至1930年。这一时期，毛泽东对创建和发展红色革命根据地的经验进行总结，撰写了《中国的红色政权为什么能够存在》（1928年）、《井冈山的斗争》（1928年）、《星星之火，可以燎原》（1930年）、《反对本本主义》（1930年）等着名文章，初步论证了中国革命走“工农武装割据”新道路的可能性和必要性，实际确立了“以乡村为中心的思想”，初步形成了农村包围城市道路的理论。因此，本题的正确答案是ABCD选项。"
    },
    {
        "题号": "35",
        "题目": "以下关于中国化了的马克思主义的基本内涵的表述中不正确的是：",
        "选项": [
            "中国化的马克思主义就是马克思主义与中国传统文化的结合",
            "中国化的马克思主义就是被中国传统文化包装了的马克思主义",
            "中国化的马克思主义就是坚持马克思主义基本原理与中国具体实际相结合",
            "中国化的马克思主义就是毛泽东思想"
        ],
        "难度": "中",
        "题型": "多选题",
        "正确答案": "A.B.D.",
        "解析": "[命题分析]本题考查的知识点是：中国化了的马克思主义的基本内涵。马克思主义的理论和中国革命的实践相结合的过程，就是马克思主义中国化的过程。所谓马克思主义中国化，就是将马克思主义基本原理同中国具体实际相结合。这一历史过程的收获就是形成中国共产党自己的理论，即中国化了的马克思主义。中国化了的马克思主义具有三个方面的因素：第一，它体现了马克思列宁主义的基本原理。第二，它包含了中华民族的优秀思想，是马克思主义基本原理和中华民族优秀思想文化的有机融合。第三，它包含了中国共产党人的实践经验。中国化了马克思主义中包含了中华民族的优秀的传统文化，而不是全部。它不是被中国传统文化包装了的马克思主义，而是既体现了马克思主义的基本原理，又融入了中华民族的优秀思想文化，是二者的有机融合。中国化的马克思主义包括毛泽东思想、邓小平理论和“三个代表”重要思想。可以说：毛泽东思想是中国化的马克思主义，但不能说马克思主义中国化就是毛泽东思想。因此，本题的正确答案是ABD选项。"
    },
    {
        "题号": "36",
        "题目": "在近现代中国的历史上，毛泽东思想的历史地位和历史作用体现在：",
        "选项": [
            "毛泽东思想是夺取中国革命胜利的理论武器",
            "毛泽东思想是社会主义中国立国建国的理论基础",
            "毛泽东思想是邓小平理论的思想渊源和理论先导",
            "毛泽东思想是中华民族团结和振兴的精神支柱"
        ],
        "难度": "中",
        "题型": "多选题",
        "正确答案": "A.B.C.D.",
        "解析": "[解析]本题考查的知识点是：毛泽东思想的历史地位和历史作用。江泽民在纪念毛泽东诞辰100周年的讲话中对毛泽东思想的历史地位进行了概括，具体体现在：第一，毛泽东思想是夺取中国革命胜利的理论武器；第二，毛泽东思想是社会主义中国立国建国的思想政治基础；第三，毛泽东思想是邓小平理论的思想渊源和理论先导；第四，中华民族团结和振兴的精神支柱；第五，毛泽东思想是马克思列宁主义发展史上承上启下、继往开来的重要阶段。因此，本题的正确答案是ABCD选项。"
    },
    {
        "题号": "37",
        "题目": "中国共产党在中国革命中战胜敌人的主要法宝是（）。",
        "选项": [
            "党的建设",
            "武装斗争",
            "整风",
            "统一战线"
        ],
        "难度": "难",
        "题型": "多选题",
        "正确答案": "A.B.D.",
        "解析": "本题考查的知识点是：毛泽东所说的三个法宝。毛泽东在《〈共产党人〉发刊词》一文中指出：“统一战线和武装斗争，是战胜敌人的两个基本武器。统一战线，是实行武装斗争的统一战线。而党的组织，则是掌握统一战线和武装斗争这两个武器以实行对敌冲锋陷阵的英勇战士。这就是三者的关系。”本题的正确答案是ABD"
    },
    {
        "题号": "38",
        "题目": "习近平总书记在同中央党校第一期县委书记研修班学员进行座谈时强调，做县委书记就要做焦裕禄的县委书记，始终做到",
        "选项": [
            "心中有党",
            "心中有民",
            "心中有责",
            "心中有戒"
        ],
        "难度": "中",
        "题型": "多选题",
        "正确答案": "A.B.C.D.",
        "解析": ""
    },
    {
        "题号": "39",
        "题目": "正式把毛泽东思想写入党章，并确立为党必须长期坚持的指导思想的是在（）",
        "选项": [
            "遵义会议",
            "党的六届六中全会",
            "党的七大",
            "党的七届二中全会"
        ],
        "难度": "中",
        "题型": "单选题",
        "正确答案": "C",
        "解析": "解析：经过六届七中全会的酝酿和讨论，1945年党的七大通过的《中国共产党党章》明确规定，“中国共产党，以马克思列宁主义的理论与中国革命的实践之统一的思想——毛泽东思想，作为自己一切工作的指针”。这标志着把毛泽东思想确立为党必须长期坚持的指导思想"
    },
    {
        "题号": "40",
        "题目": "（）确定了实行土地革命和武装起义的方针",
        "选项": [
            "洛川会议",
            "遵义会议",
            "党的七大",
            "八七会议"
        ],
        "难度": "中",
        "题型": "单选题",
        "正确答案": "D",
        "解析": "解析：教材第17页土地革命战争时期,党从残酷的现实斗争中认识到,夺取中国革命胜利，就必须坚持以武装的革命反对武装的反革命 。八七会议确定实行土地革命和武装起义的方针 。"
    },
    {
        "题号": "41",
        "题目": "（）是毛泽东思想的精髓",
        "选项": [
            "群众路线",
            "实事求是",
            "统一战线",
            "独立自主"
        ],
        "难度": "中",
        "题型": "单选题",
        "正确答案": "B",
        "解析": "解析：教材27页。实事求是是毛泽东思想的基本点，是毛泽东思想的精髓 。"
    },
    {
        "题号": "42",
        "题目": "（）关系党的生死存亡",
        "选项": [
            "党同人民群众的联系问题",
            "党风问题",
            "实践创新问题",
            "文化自信问题"
        ],
        "难度": "中",
        "题型": "多选题",
        "正确答案": "A.B.",
        "解析": "解析：教材30页。党风问题、党同人民群众的联系问题关系党的生死存亡。"
    },
    {
        "题号": "43",
        "题目": "无产阶级及其政党要实现自己对同盟者的领导，必须具备两个条件（）",
        "选项": [
            "率领被领导者向着共同的敌人作坚决斗争并取得胜利",
            "对被领导者给以物质利益。至少不损害其利益，同时给以政治教育",
            "战略上要藐视敌人 ，战术上要重视敌人",
            "实行利用矛盾、争取多数、反对少数"
        ],
        "难度": "中",
        "题型": "多选题",
        "正确答案": "A.B.",
        "解析": "解析：教材24页"
    },
    {
        "题号": "44",
        "题目": "（）从组织上确立了党对军队的领导，是 建设无产阶级领导的新型人民军队的重要开端",
        "选项": [
            "秋收起义",
            "延安整风",
            "三湾改编",
            "八七会议"
        ],
        "难度": "中",
        "题型": "单选题",
        "正确答案": "C",
        "解析": "解析：教材23页 “三湾改编 ”，创造性地将支部建在连上，成立各级士兵委员会， 实行民主制度，在政治上官兵平等。 由此开始改变了起义军中旧军队的习气和不良作风，从组织上确立 了党对军队的领导，是 建设无产阶级领导的新型人民军队的重要开端"
    },
    {
        "题号": "45",
        "题目": "近代中国的基本国情是（）",
        "选项": [
            "半殖民地",
            "半封建",
            "半殖民地半封建",
            "殖民地"
        ],
        "难度": "中",
        "题型": "单选题",
        "正确答案": "C",
        "解析": "解析：教材P39"
    },
    {
        "题号": "46",
        "题目": "近代中国最主要的矛盾是（）",
        "选项": [
            "帝国主义和中华民族的矛盾",
            "封建主义和人民大众的矛盾",
            "官僚资本主义和人民大众的矛盾",
            "帝国主义和官僚资本主义的矛盾"
        ],
        "难度": "难",
        "题型": "单选题",
        "正确答案": "A",
        "解析": "解析：教材P41"
    },
    {
        "题号": "47",
        "题目": "中国资产阶级民主革命进入新民主主义革命的崭新阶段的标志是()",
        "选项": [
            "十月革命",
            "五四运动",
            "新文化运动",
            "辛亥革命"
        ],
        "难度": "难",
        "题型": "单选题",
        "正确答案": "B",
        "解析": "解析：教材P42"
    },
    {
        "题号": "48",
        "题目": "新民主主义革命的总路线是在（）提出的",
        "选项": [
            "《中国革命和中国共产党》",
            "《新民主主义论》",
            "《在晋绥干部会议上的讲话》",
            "《论联合政府》"
        ],
        "难度": "易",
        "题型": "单选题",
        "正确答案": "C",
        "解析": "解析：教材P45"
    },
    {
        "题号": "49",
        "题目": "新民主主义革命的首要对象是（）",
        "选项": [
            "帝国主义",
            "封建主义",
            "官僚资本主义",
            "民族资本主义"
        ],
        "难度": "难",
        "题型": "单选题",
        "正确答案": "A",
        "解析": "解析：教材P46"
    },
    {
        "题号": 50,
        "题目": "帝国主义统治中国和封建军阀实行专制统治的社会基础是（）",
        "选项": [
            "帝国主义",
            "封建地主阶级",
            "官僚资本主义",
            "民族资产阶级"
        ],
        "难度": "中",
        "题型": "单选题",
        "正确答案": "B",
        "解析": "解析：教材P46"
    },
    {
        "题号": 51,
        "题目": "中国革命最基本的动力是（）",
        "选项": [
            "无产阶级",
            "农民",
            "城市小资产阶级",
            "民族资产阶级"
        ],
        "难度": "中",
        "题型": "单选题",
        "正确答案": "A",
        "解析": "解析：教材P47"
    },
    {
        "题号": 52,
        "题目": "中国革命的主力军是（）",
        "选项": [
            "无产阶级",
            "农民",
            "城市小资产阶级",
            "民族资产阶级"
        ],
        "难度": "中",
        "题型": "单选题",
        "正确答案": "B",
        "解析": "解析：教材P48"
    },
    {
        "题号": 53,
        "题目": "毛泽东建军思想的核心是（）",
        "选项": [
            "坚持党对军队的绝对领导",
            "坚持全心全意为人民服务",
            "开展革命的政治工作",
            "坚持正确的战略战术原则"
        ],
        "难度": "易",
        "题型": "单选题",
        "正确答案": "A",
        "解析": "解析：教材P62"
    },
    {
        "题号": 54,
        "题目": "新民主主义革命的领导力量是（）",
        "选项": [
            "无产阶级",
            "农民",
            "城市小资产阶级",
            "民族资产阶级"
        ],
        "难度": "中",
        "题型": "单选题",
        "正确答案": "A",
        "解析": "解析：教材P49"
    },
    {
        "题号": 55,
        "题目": "新民主主义革命的主要内容是（）",
        "选项": [
            "没收封建土地阶级的土地归农民所有",
            "没收官僚资产阶级的垄断资本归新民主主义国家所有",
            "保护民族工商业",
            "推翻帝国主义统治"
        ],
        "难度": "难",
        "题型": "单选题",
        "正确答案": "A",
        "解析": "解析：教材P53"
    },
    {
        "题号": 56,
        "题目": "新民主主义革命道路是（）",
        "选项": [
            "城市暴动",
            "农村包围城市",
            "武装夺取政权",
            "农村包围城市，武装夺取政权"
        ],
        "难度": "难",
        "题型": "单选题",
        "正确答案": "D",
        "解析": "解析：教材P56"
    },
    {
        "题号": 57,
        "题目": "新民主主义革命的对象是（）",
        "选项": [
            "帝国主义",
            "封建主义",
            "官僚资本主义",
            "民族资本主义"
        ],
        "难度": "中",
        "题型": "多选题",
        "正确答案": "A.B.C.",
        "解析": "解析：教材P45"
    },
    {
        "题号": 58,
        "题目": "新民主主义革命的动力是（）",
        "选项": [
            "无产阶级",
            "农民",
            "城市小资产阶级",
            "民族资产阶级"
        ],
        "难度": "中",
        "题型": "多选题",
        "正确答案": "A.B.C.D.",
        "解析": ""
    },
    {
        "题号": 59,
        "题目": "新民主主义革命的经济纲领是（）",
        "选项": [
            "没收封建地主阶级的土地归农民所有",
            "没收官僚资产阶级的垄断资本归新民主主义国家所有",
            "保护民族工商业",
            "推翻帝国主义统治"
        ],
        "难度": "中",
        "题型": "多选题",
        "正确答案": "A.B.C.",
        "解析": "教材P53"
    },
    {
        "题号": 60,
        "题目": "新民主主义革命的三大法宝是（）",
        "选项": [
            "统一战线",
            "群众路线",
            "武装斗争",
            "党的建设"
        ],
        "难度": "易",
        "题型": "多选题",
        "正确答案": "A.C.D.",
        "解析": "解析：教材59"
    },
    {
        "题号": 61,
        "题目": "新民主主义革命属于（）",
        "选项": [
            "资产阶级民主主义革命",
            "无产阶级社会主义革命 性质",
            "世界资产阶级革命范畴",
            "世界无产阶级社会主义革命的一部分"
        ],
        "难度": "难",
        "题型": "多选题",
        "正确答案": "A.D.",
        "解析": "解析：教材51"
    },
    {
        "题号": 62,
        "题目": "中华人民共和国的成立，标志着中国已从半殖民地半封建社会进入到",
        "选项": [
            "资本主义社会",
            "新民主主义社会",
            "社会主义社会",
            "社会主义初级阶段"
        ],
        "难度": "难",
        "题型": "单选题",
        "正确答案": "B",
        "解析": ""
    },
    {
        "题号": 63,
        "题目": "新民主主义社会形态是",
        "选项": [
            "独立的社会形态",
            "半独立的社会形态",
            "过渡性的社会形态",
            "半独立半过渡的社会形态"
        ],
        "难度": "难",
        "题型": "单选题",
        "正确答案": "C",
        "解析": ""
    },
    {
        "题号": 64,
        "题目": "在新民主主义经济成分中，具有社会主义性质的是",
        "选项": [
            "国营经济",
            "合作社经济",
            "个体经济",
            "国家资本主义经济和私人资本主义经济"
        ],
        "难度": "中",
        "题型": "单选题",
        "正确答案": "A",
        "解析": ""
    },
    {
        "题号": 65,
        "题目": "建国初期，随着土地改革的基本完成，我国社会主要矛盾逐步变为",
        "选项": [
            "工人阶级和地主阶级的矛盾",
            "工人阶级和农民阶级的矛盾",
            "工人阶级和小资产阶级的矛盾",
            "工人阶级和资产阶级的矛盾"
        ],
        "难度": "中",
        "题型": "单选题",
        "正确答案": "D",
        "解析": ""
    },
    {
        "题号": 66,
        "题目": "过渡时期总路线的主体是",
        "选项": [
            "实现社会主义工业化",
            "实现对农业的社会主义改造",
            "实现对手工业的社会主义改造",
            "实现对资本主义工商业的社会主义改造"
        ],
        "难度": "易",
        "题型": "单选题",
        "正确答案": "A",
        "解析": ""
    },
    {
        "题号": 67,
        "题目": "在农业社会主义改造中具有半社会主义性质的发展阶段是",
        "选项": [
            "发展互助组",
            "建立初级社",
            "发展高级社",
            "实行家庭联产承包责任制"
        ],
        "难度": "中",
        "题型": "单选题",
        "正确答案": "B",
        "解析": ""
    },
    {
        "题号": 68,
        "题目": "我国对资本主义工商业社会主义改造采取的政策是",
        "选项": [
            "互助合作",
            "计划订货",
            "和平赎买",
            "统购包销"
        ],
        "难度": "中",
        "题型": "单选题",
        "正确答案": "C",
        "解析": ""
    },
    {
        "题号": 69,
        "题目": "社会主义改造围绕的中心任务是",
        "选项": [
            "引导个体农业走集体化道路",
            "引导个体手工业者走集体化道路",
            "改造私人资本主义工商业",
            "社会主义工业化建设"
        ],
        "难度": "中",
        "题型": "单选题",
        "正确答案": "D",
        "解析": ""
    },
    {
        "题号": 70,
        "题目": "初级形式的国家资本主义对资本主义私营商业采取的形式是",
        "选项": [
            "经销代销",
            "委托加工",
            "统购包销",
            "计划订货"
        ],
        "难度": "中",
        "题型": "多选题",
        "正确答案": "A.B.C.D.",
        "解析": ""
    },
    {
        "题号": 71,
        "题目": "高级形式的国家资本主义是",
        "选项": [
            "经销代销",
            "统购包销",
            "互助合作",
            "公私合营"
        ],
        "难度": "易",
        "题型": "单选题",
        "正确答案": "D",
        "解析": ""
    },
    {
        "题号": 72,
        "题目": "在农业的社会主义改造中，党在农村的依靠力量是",
        "选项": [
            "富农",
            "雇农",
            "上中农",
            "贫下中农"
        ],
        "难度": "难",
        "题型": "单选题",
        "正确答案": "D",
        "解析": ""
    },
    {
        "题号": 73,
        "题目": "我国社会主义改造基本完成是在",
        "选项": [
            "1949年",
            "1952年",
            "1956年",
            "1978年"
        ],
        "难度": "难",
        "题型": "单选题",
        "正确答案": "C",
        "解析": ""
    },
    {
        "题号": 74,
        "题目": "社会主义基本制度在中国的确立的标志是",
        "选项": [
            "新民主主义革命的胜利",
            "社会主义改造的基本完成",
            "新中国的成立",
            "全国大陆的解放"
        ],
        "难度": "中",
        "题型": "单选题",
        "正确答案": "B",
        "解析": ""
    },
    {
        "题号": 75,
        "题目": "社会主义基本制度在中国的确立的标志是",
        "选项": [
            "新民主主义革命的胜利",
            "社会主义改造的基本完成",
            "新中国的成立",
            "全国大陆的解放"
        ],
        "难度": "中",
        "题型": "单选题",
        "正确答案": "B",
        "解析": ""
    },
    {
        "题号": 76,
        "题目": "《中华人民共和国宪法》的制定和颁布施行是在",
        "选项": [
            "1949年",
            "1952年",
            "1954年",
            "1956年"
        ],
        "难度": "中",
        "题型": "单选题",
        "正确答案": "C",
        "解析": ""
    },
    {
        "题号": 77,
        "题目": "我国阶级剥削制度被消灭的标志是",
        "选项": [
            "中华人民共和国的成立",
            "全国大陆的解放",
            "土地改革的完成",
            "社会主义改造的基本完成"
        ],
        "难度": "中",
        "题型": "单选题",
        "正确答案": "D",
        "解析": ""
    },
    {
        "题号": 78,
        "题目": "我国阶级剥削制度被消灭的标志是",
        "选项": [
            "中华人民共和国的成立",
            "全国大陆的解放",
            "土地改革的完成",
            "社会主义改造的基本完成"
        ],
        "难度": "中",
        "题型": "单选题",
        "正确答案": "D",
        "解析": ""
    },
    {
        "题号": 79,
        "题目": "对个体农业和手工业实行社会主义改造的方针是",
        "选项": [
            "趁热打铁，积极领导",
            "自愿互利，国家帮助",
            "积极领导，稳步前进",
            "国家帮助，典型示范"
        ],
        "难度": "中",
        "题型": "单选题",
        "正确答案": "C",
        "解析": ""
    },
    {
        "题号": 80,
        "题目": "对资本主义工商业进行社会主义改造的主要方法是",
        "选项": [
            "和平赎买",
            "统购统销",
            "公私合营",
            "合作化"
        ],
        "难度": "难",
        "题型": "单选题",
        "正确答案": "A",
        "解析": ""
    },
    {
        "题号": 81,
        "题目": "建国初期的新民主主义经济成分有",
        "选项": [
            "合作社经济",
            "国家资本主义经济和私人资本经济",
            "个体经济",
            "国营经济"
        ],
        "难度": "中",
        "题型": "多选题",
        "正确答案": "A.B.C.D.",
        "解析": ""
    },
    {
        "题号": 82,
        "题目": "关于过渡时期总路线主要内容“一化”和“三改”关系的正确阐述是",
        "选项": [
            "“主体”和“两翼”的关系",
            "社会主义工业化和社会主义改造紧密结合",
            "二者互相牵制、互为矛盾",
            "二者相辅相成、互相促进"
        ],
        "难度": "易",
        "题型": "多选题",
        "正确答案": "A.B.D.",
        "解析": ""
    },
    {
        "题号": 83,
        "题目": "“四马分肥”是指企业的利润按以下几方面进行分配",
        "选项": [
            "国家所得税",
            "资方红利",
            "企业公积金",
            "工人福利费"
        ],
        "难度": "易",
        "题型": "多选题",
        "正确答案": "A.B.C.D.",
        "解析": ""
    },
    {
        "题号": 84,
        "题目": "手工业的社会主义改造经历的主要步骤有",
        "选项": [
            "办手工业供销小组",
            "办手工业供销合作社",
            "建立手工业生产合作社",
            "实行全行业公私合营"
        ],
        "难度": "易",
        "题型": "多选题",
        "正确答案": "A.B.C.",
        "解析": ""
    },
    {
        "题号": 85,
        "题目": "对农业社会主义改造遵循的原则是",
        "选项": [
            "和平赎买",
            "国家帮助",
            "自愿互利",
            "典型示范"
        ],
        "难度": "易",
        "题型": "多选题",
        "正确答案": "B.C.D.",
        "解析": ""
    },
    {
        "题号": 86,
        "题目": "农业社会主义大体上经历了（）发展阶段",
        "选项": [
            "互助组",
            "初级社",
            "中级社",
            "高级社"
        ],
        "难度": "中",
        "题型": "多选题",
        "正确答案": "A.B.D.",
        "解析": ""
    },
    {
        "题号": 87,
        "题目": "在进行社会主义改造、向社会主义过渡的进程中，中国共产党积累了丰富的历史经验，包括",
        "选项": [
            "坚持社会主义工业化建设与社会主义改造同时并举",
            "采取积极引导、逐步过渡的方式",
            "用和平方法进行改造",
            "采用从低级到高级的国家资本主义的过渡形式"
        ],
        "难度": "易",
        "题型": "多选题",
        "正确答案": "A.B.C.",
        "解析": ""
    },
    {
        "题号": 88,
        "题目": "对资本主义工商业实行和平赎买，有利于",
        "选项": [
            "发挥私营工商业在国计民生方面的积极作用，促进国民经济发展",
            "争取和团结民族资产阶级，有利于团结各民主党派和各界爱国民主人士，巩固和发展统一战线",
            "发挥民族资产阶级中大多数人的知识、才能、技术专长和管理经验",
            "争取和团结那些原来同资产阶级相联系的知识分子为社会主义建设服务"
        ],
        "难度": "难",
        "题型": "多选题",
        "正确答案": "A.B.C.D.",
        "解析": ""
    },
    {
        "题号": 89,
        "题目": "调动一切积极因素为社会主义事业服务，必须坚持（）",
        "选项": [
            "独立自主",
            "中国共产党的领导",
            "社会主义",
            "对外开放"
        ],
        "难度": "难",
        "题型": "单选题",
        "正确答案": "B",
        "解析": ""
    },
    {
        "题号": 90,
        "题目": "调动一切积极因素为社会主义事业服务，必须发展（）",
        "选项": [
            "社会主义经济",
            "社会主义文化",
            "社会主义民主政治",
            "社会主义德治"
        ],
        "难度": "难",
        "题型": "单选题",
        "正确答案": "C",
        "解析": ""
    },
    {
        "题号": 91,
        "题目": "调动一切（）为社会主义事业服务，是党关于社会主义建设的一条极为重要的方针。",
        "选项": [
            "重要因素",
            "积极因素",
            "有利因素",
            "有利条件"
        ],
        "难度": "易",
        "题型": "单选题",
        "正确答案": "B",
        "解析": ""
    },
    {
        "题号": 92,
        "题目": "毛泽东所作的（）的报告，系统论述了社会主义社会矛盾的理论",
        "选项": [
            "《矛盾论》",
            "《实践论》",
            "《关于正确处理人民内部矛盾的问题》",
            "《论十大关系》"
        ],
        "难度": "中",
        "题型": "单选题",
        "正确答案": "C",
        "解析": ""
    },
    {
        "题号": 93,
        "题目": "党的八大正确分析了中国社会主要矛盾的变化，指出我国社会主要矛盾，已经是人民对于建立先进的工业国的要求同落后的（）的现实之间的矛盾",
        "选项": [
            "经济",
            "农业经济",
            "农业国",
            "工业经济"
        ],
        "难度": "难",
        "题型": "单选题",
        "正确答案": "C",
        "解析": ""
    },
    {
        "题号": 94,
        "题目": "党的八大正确分析了中国社会主要矛盾的变化，指出我国社会主要矛盾，已经是人民对于（）迅速发展的需要同当前经济文化不能满足人民需要的状况之间的矛盾",
        "选项": [
            "经济",
            "文化",
            "生态",
            "经济文化"
        ],
        "难度": "难",
        "题型": "单选题",
        "正确答案": "D",
        "解析": ""
    },
    {
        "题号": 95,
        "题目": "敌我矛盾是根本利益对立基础上的矛盾，因而是（）的矛盾",
        "选项": [
            "对抗性",
            "非对抗性",
            "对立性",
            "非对立性"
        ],
        "难度": "难",
        "题型": "单选题",
        "正确答案": "A",
        "解析": ""
    },
    {
        "题号": 96,
        "题目": "人民内部矛盾是在人民根本利益一致基础上的矛盾，因而是（）的矛盾",
        "选项": [
            "对抗性",
            "非对抗性",
            "对立性",
            "非对立性"
        ],
        "难度": "难",
        "题型": "单选题",
        "正确答案": "B",
        "解析": ""
    },
    {
        "题号": 97,
        "题目": "关于正确处理人民内部矛盾的方针，用（）的方法解决人民内部矛盾，这是一个总方针",
        "选项": [
            "专政",
            "法治",
            "民主",
            "德治"
        ],
        "难度": "难",
        "题型": "单选题",
        "正确答案": "C",
        "解析": ""
    },
    {
        "题号": 98,
        "题目": "关于正确处理人民内部矛盾的问题是社会主义国家（）生活的主题。",
        "选项": [
            "经济",
            "政治",
            "文化",
            "社会"
        ],
        "难度": "难",
        "题型": "单选题",
        "正确答案": "B",
        "解析": ""
    },
    {
        "题号": 99,
        "题目": "实现（）是中国近代以来历史发展的必然要求，也是民族独立和国家富强的必要条件。",
        "选项": [
            "现代化",
            "工业化",
            "机械化",
            "信息化"
        ],
        "难度": "中",
        "题型": "单选题",
        "正确答案": "B",
        "解析": ""
    },
    {
        "题号": 100,
        "题目": "（），为我国实现工业化提供了根本的政治前提。",
        "选项": [
            "中华人民共和国的成立",
            "中华民族的独立",
            "抗日战争胜利",
            "解放战争胜利"
        ],
        "难度": "难",
        "题型": "单选题",
        "正确答案": "A",
        "解析": ""
    },
    {
        "题号": 101,
        "题目": "走中国工业化道路，必须调整和完善（）。",
        "选项": [
            "分配制度",
            "所有制结构",
            "经济体制",
            "运行机制"
        ],
        "难度": "中",
        "题型": "单选题",
        "正确答案": "B",
        "解析": ""
    },
    {
        "题号": 102,
        "题目": "（）是无产阶级政党的根本政治原则，是指导党内生活的基本准则。",
        "选项": [
            "党内民主",
            "民主集中制",
            "民主制度",
            "代表制度"
        ],
        "难度": "中",
        "题型": "单选题",
        "正确答案": "B",
        "解析": ""
    },
    {
        "题号": 103,
        "题目": "毛泽东提出，在探索中国社会主义建设道路的过程中，社会主义又可分为两个阶段，第一个阶段是（），第二个阶段是（）",
        "选项": [
            "不发达的社会主义",
            "欠发达的社会主义",
            "比较发达的社会主义",
            "发达的社会主义"
        ],
        "难度": "中",
        "题型": "多选题",
        "正确答案": "A.C.",
        "解析": ""
    },
    {
        "题号": 104,
        "题目": "关于社会主义社会两类性质的矛盾，毛泽东强调，在我们面前有两类社会矛盾，这就是（）和（）",
        "选项": [
            "阶级矛盾",
            "敌我矛盾",
            "人民内部矛盾",
            "外部矛盾"
        ],
        "难度": "中",
        "题型": "多选题",
        "正确答案": "B.C.",
        "解析": ""
    },
    {
        "题号": 105,
        "题目": "关于中国工业化道路，毛泽东提出了以（）为基础，以（）为主导，以（）为序发展国民经济的总方针。",
        "选项": [
            "农业",
            "工业",
            "农轻重",
            "服务业"
        ],
        "难度": "易",
        "题型": "多选题",
        "正确答案": "A.B.C.",
        "解析": ""
    },
    {
        "题号": 106,
        "题目": "社会主义现代化的战略目标，是要把中国建设成为一个具有（）、（）、（）和（）的强国。",
        "选项": [
            "现代农业",
            "现代工业",
            "现代国防",
            "现代科学技术",
            "现代服务业"
        ],
        "难度": "中",
        "题型": "多选题",
        "正确答案": "A.B.C.D.",
        "解析": ""
    },
    {
        "题号": 107,
        "题目": "走中国工业化道路，必须发展（）和（）。",
        "选项": [
            "科学技术",
            "经济文化",
            "社会政治",
            "文化教育"
        ],
        "难度": "中",
        "题型": "多选题",
        "正确答案": "A.D.",
        "解析": ""
    },
    {
        "题号": 108,
        "题目": "走中国现代化道路，必须积极探索适合我国情况的（）和（）。",
        "选项": [
            "分配制度",
            "经济体制",
            "运行机制",
            "所有制"
        ],
        "难度": "中",
        "题型": "多选题",
        "正确答案": "B.C.",
        "解析": ""
    },
    {
        "题号": 109,
        "题目": "社会主义建设道路初步探索，为开创中国特色社会主义提供了（）、（）、（）",
        "选项": [
            "宝贵经验",
            "有利条件",
            "理论准备",
            "物质基础"
        ],
        "难度": "易",
        "题型": "多选题",
        "正确答案": "A.C.D.",
        "解析": ""
    },
    {
        "题号": 110,
        "题目": "社会主义建设道路探索实践证明，中国要实现社会主义现代化，必须发展（），加强（）。",
        "选项": [
            "社会主义民主",
            "社会主义文化",
            "社会主义法制",
            "社会主义经济"
        ],
        "难度": "中",
        "题型": "多选题",
        "正确答案": "A.C.",
        "解析": ""
    },
    {
        "题号": 111,
        "题目": "()以后，以邓小平同志为主要代表的中国共产党人，领导全党和全国人民，结合中国实际，不断探索和回答什么是社会主义、怎样建设社会主义这一基本问题，开创了中国特色社会主义的伟大事业。",
        "选项": [
            "党的七届二中全会",
            "党的十一届三中全会",
            "党的十二大",
            "党的十三大"
        ],
        "难度": "难",
        "题型": "单选题",
        "正确答案": "B",
        "解析": ""
    },
    {
        "题号": 112,
        "题目": "党的十八大以来，世界之变、时代之变、历史之变正以前所未有的方式展开，（）加速演进。",
        "选项": [
            "中华民族伟大复兴战略全局",
            "世界百年未有之大变局",
            "五位一体总体布局",
            "多极化国际格局"
        ],
        "难度": "难",
        "题型": "单选题",
        "正确答案": "B",
        "解析": ""
    },
    {
        "题号": 113,
        "题目": "以江泽民同志为主要代表的中国共产党人科学判断党的历史方位、深刻总结历史经验，创造性地回答了（）这一重大问题。",
        "选项": [
            "什么是社会主义、怎样建设社会主义",
            "建设什么样的党、怎样建设党",
            "实现什么样的发展、怎样发展",
            "坚持和发展什么样的中国特色社会主义、怎样坚持和发展中国特色社会主义"
        ],
        "难度": "中",
        "题型": "单选题",
        "正确答案": "B",
        "解析": ""
    },
    {
        "题号": 114,
        "题目": "1984年，党的十二届三中全会作出了《中共中央关于经济体制改革的决定》，提出了社会主义经济是在公有制基础上的（）。",
        "选项": [
            "计划经济",
            "有计划的商品经济",
            "市场经济",
            "商品经济"
        ],
        "难度": "难",
        "题型": "单选题",
        "正确答案": "B",
        "解析": ""
    },
    {
        "题号": 115,
        "题目": "1987年召开的党的十三大第一次比较系统地论述了我国（）理论。",
        "选项": [
            "改革开放新时期",
            "社会主义建设新时期",
            "中国特色社会主义新时代",
            "社会主义初级阶段"
        ],
        "难度": "中",
        "题型": "单选题",
        "正确答案": "D",
        "解析": ""
    },
    {
        "题号": 116,
        "题目": "2007年，（）对科学发展观的理论定位、理论依据、理论内涵作了全面阐述，把科学发展观写入党章。",
        "选项": [
            "党的十五大",
            "党的十六大",
            "党的十七大",
            "党的十八大"
        ],
        "难度": "难",
        "题型": "单选题",
        "正确答案": "C",
        "解析": ""
    },
    {
        "题号": 117,
        "题目": "党的十九大、十九届六中全会提出的（）概括了习近平新时代中国特色社会主义思想的主要内容。",
        "选项": [
            "“十个明确”",
            "“十四个坚持”",
            "“十三个方面成就”",
            "“四个全面”"
        ],
        "难度": "中",
        "题型": "多选题",
        "正确答案": "A.B.C.",
        "解析": ""
    },
    {
        "题号": 118,
        "题目": "2000年5月14日，江泽民在江苏、浙江、上海党建工作座谈会上明确提出，推进党的（），都应该贯穿“三个代表”要求，要把“三个代表”要求贯彻落实到党的全部工作中去。",
        "选项": [
            "思想建设",
            "政治建设",
            "组织建设",
            "作风建设"
        ],
        "难度": "中",
        "题型": "多选题",
        "正确答案": "A.B.C.D.",
        "解析": ""
    },
    {
        "题号": 119,
        "题目": "20世纪70年代，整个世界发生着大变动大调整，最显著的变化，就是（）成为时代主题。",
        "选项": [
            "和平",
            "世界多极化",
            "经济全球化",
            "发展"
        ],
        "难度": "中",
        "题型": "多选题",
        "正确答案": "A.D.",
        "解析": ""
    },
    {
        "题号": 120,
        "题目": "中国特色社会主义理论体系，是在（）的基础上形成并不断发展的。",
        "选项": [
            "认真总结我国社会主义建设正反两方面的历史经验",
            "应对全球共同挑战",
            "解决人类发展重大问题",
            "科学判断党和国家发展所处历史方位"
        ],
        "难度": "难",
        "题型": "多选题",
        "正确答案": "A.D.",
        "解析": ""
    },
    {
        "题号": 121,
        "题目": "党的（）正式提出“邓小平理论”这一概念，深刻阐述了邓小平理论的历史地位和指导意义",
        "选项": [
            "十二大",
            "十三大",
            "十四大",
            "十五大"
        ],
        "难度": "易",
        "题型": "单选题",
        "正确答案": "D",
        "解析": ""
    },
    {
        "题号": 122,
        "题目": "习近平新时代中国特色社会主义思想科学回答了（）等重大时代课题",
        "选项": [
            "建设什么样的长期执政的马克思主义政党，怎样建设长期执政的马克思主义政党",
            "建设什么样的社会主义现代化强国，怎样建设社会主义现代化强国",
            "建成和发展什么样的中国特色社会主义，怎样建成和发展中国特色社会主义",
            "实现什么样的发展，怎样发展"
        ],
        "难度": "易",
        "题型": "多选题",
        "正确答案": "A.B.C.",
        "解析": ""
    },
    {
        "题号": 123,
        "题目": "邓小平( )南方谈话，科学总结党的十一届三中全会以来的实践探索和基本经验。",
        "选项": [
            "1991年",
            "1992年",
            "1993年",
            "1994年"
        ],
        "难度": "难",
        "题型": "单选题",
        "正确答案": "B",
        "解析": ""
    },
    {
        "题号": 124,
        "题目": "( )把邓小平理论同马克思列宁主义、毛泽东思想一起作为党的指导思想写入党章。",
        "选项": [
            "党的十四大",
            "党的十五大",
            "党的十六大",
            "党的十七大"
        ],
        "难度": "难",
        "题型": "单选题",
        "正确答案": "B",
        "解析": ""
    },
    {
        "题号": 125,
        "题目": "1992年邓小平南方讲话，深刻回答了长期束缚人们思想的许多认识问题，突出的是（）",
        "选项": [
            "发展速度与提高经济效益的问题",
            "依法治国与加强党的领导的问题",
            "物质文明建设与精神文明建设问题",
            "姓“资”姓“社”问题"
        ],
        "难度": "中",
        "题型": "单选题",
        "正确答案": "D",
        "解析": ""
    },
    {
        "题号": 126,
        "题目": "邓小平指出：“我们现在所干的事业是一项新事业，马克思没有讲过，我们的前人没有做过，其他社会主义国家也没有干过，……我们只能在干中学，在实践中摸索。”这段话表明邓小平理论产生的（）",
        "选项": [
            "时代背景是当今世界的时代特征和国际形势",
            "历史依据是中国和其他国家社会主义建设正反两方面的历史经验",
            "现实依据是我国改革开放和现代化建设的崭新实践",
            "理论依据是马列主义毛泽东思想"
        ],
        "难度": "中",
        "题型": "单选题",
        "正确答案": "C",
        "解析": ""
    },
    {
        "题号": 127,
        "题目": "1975年，邓小平主持国务院工作，为扭转混乱局面，在经济领域的整顿以（）突破口。",
        "选项": [
            "铁路部门",
            "工业部门",
            "农业系统",
            "军队系统"
        ],
        "难度": "易",
        "题型": "单选题",
        "正确答案": "A",
        "解析": ""
    },
    {
        "题号": 128,
        "题目": "1978年3月，全国科学技术大会在北京召开，邓小平在开幕式上的讲话强调，四个现代化，关键是（）。",
        "选项": [
            "农业现代化",
            "教育现代化",
            "科学技术现代化",
            "工业现代化"
        ],
        "难度": "难",
        "题型": "单选题",
        "正确答案": "C",
        "解析": ""
    },
    {
        "题号": 129,
        "题目": "在党的十一届三中全会前召开的中央工作会议上，邓小平发表了题为（）的纲领性讲话，实际上成为中国实行改革开放的政治宣言书。",
        "选项": [
            "《“两个凡是”不符合马克思主义》",
            "《完整地准确地理解毛泽东思想》",
            "《解放思想，实事求是，团结一致向前看》",
            "《党和国家领导制度的改革》"
        ],
        "难度": "难",
        "题型": "单选题",
        "正确答案": "C",
        "解析": ""
    },
    {
        "题号": 130,
        "题目": "邓小平理论系统回答的重大时代课题是（）。",
        "选项": [
            "什么是马克思主义、怎么样发展马克思主义",
            "什么是社会主义、怎样建设社会主义",
            "建设什么样的党、怎么样建设党",
            "实现什么样的发展、怎么样实现这样的发展"
        ],
        "难度": "中",
        "题型": "单选题",
        "正确答案": "B",
        "解析": ""
    },
    {
        "题号": 131,
        "题目": "1979年3月30日，邓小平在党的理论工作务虚会上讲话强调，必须坚持（）。",
        "选项": [
            "四项基本原则",
            "解放思想，实事求是",
            "以经济建设为中心",
            "改革开放"
        ],
        "难度": "中",
        "题型": "单选题",
        "正确答案": "A",
        "解析": ""
    },
    {
        "题号": 132,
        "题目": "从1987年党的十三大到1992年邓小平南方谈话和党的十四大，邓小平理论（）。",
        "选项": [
            "处于萌芽时期",
            "初步形成",
            "逐步展开并形成轮廓",
            "走向成熟并形成理论体系"
        ],
        "难度": "难",
        "题型": "单选题",
        "正确答案": "D",
        "解析": ""
    },
    {
        "题号": 133,
        "题目": "邓小平理论的精髓是（）。",
        "选项": [
            "改革开放",
            "解放思想，实事求是",
            "社会主义市场经济",
            "抓住时机，发展自己"
        ],
        "难度": "难",
        "题型": "单选题",
        "正确答案": "B",
        "解析": ""
    },
    {
        "题号": 134,
        "题目": "邓小平提出的“三个有利于”标准具有内在联系性，其中最基本的是（）。",
        "选项": [
            "生产力标准",
            "人民生活水平标准",
            "综合国力标准",
            "社会文化标准"
        ],
        "难度": "难",
        "题型": "单选题",
        "正确答案": "A",
        "解析": ""
    },
    {
        "题号": 135,
        "题目": "坚持以经济建设为中心，从根本上说是由（）决定的。",
        "选项": [
            "当前的国际环境",
            "社会主义初级阶段的主要矛盾",
            "实现社会主义现代化的历史任务",
            "实现社会主义建设发展战略的目标"
        ],
        "难度": "中",
        "题型": "单选题",
        "正确答案": "B",
        "解析": ""
    },
    {
        "题号": 136,
        "题目": "在经济发展中起第一位变革作用的是",
        "选项": [
            "科学技术",
            "资源",
            "人才",
            "劳动工具"
        ],
        "难度": "中",
        "题型": "单选题",
        "正确答案": "A",
        "解析": ""
    },
    {
        "题号": 137,
        "题目": "首先明确提出“一个国家，两种制度”概念的是",
        "选项": [
            "毛泽东",
            "周恩来",
            "邓小平",
            "江泽民"
        ],
        "难度": "易",
        "题型": "单选题",
        "正确答案": "C",
        "解析": ""
    },
    {
        "题号": 138,
        "题目": "1977年8月，邓小平主持召开科学和教育工作座谈会。这次座谈会提出的要求包括（）",
        "选项": [
            "澄清对教育战线“两个估计”的是非",
            "重新树立全民族尊重知识的风尚",
            "改善科技人员生活和工作待遇",
            "建设社会主义“四个现代化”",
            "改革高等学校现行招生制度，立即恢复文化考试"
        ],
        "难度": "易",
        "题型": "多选题",
        "正确答案": "A.B.C.E.",
        "解析": ""
    },
    {
        "题号": 139,
        "题目": "1979年3月30日，邓小平代表中共中央在北京召开的理论工作务虚会上作了题为《坚持四项基本原则》的讲话。邓小平在讲话中提出必须坚持的“四项基本原则”，具体内容是（）",
        "选项": [
            "必须坚持社会主义道路",
            "必须坚持一个中国原则",
            "必须坚持无产阶级专政",
            "必须坚持中国共产党的领导",
            "必须坚持马列主义、毛泽东思想"
        ],
        "难度": "中",
        "题型": "多选题",
        "正确答案": "A.C.D.E.",
        "解析": ""
    },
    {
        "题号": 140,
        "题目": "邓小平指出：“我们坚信马克思主义，但是马克思主义必须与中国实际相结合。只有结合中国实际的马克思主义，才是我们所需要的真正的马克思主义。”这说明（）",
        "选项": [
            "马克思主义具有与时俱进的理论品质",
            "离开中国的具体国情谈马克思主义没有意义",
            "邓小平理论与马克思主义的理论观点是一致的",
            "强烈的现实性是邓小平理论的本质特征"
        ],
        "难度": "易",
        "题型": "多选题",
        "正确答案": "A.B.D.",
        "解析": ""
    },
    {
        "题号": 141,
        "题目": "1978年中共十一届三中全会实现的三大历史转变是（）",
        "选项": [
            "从以“阶级斗争为纲”转到以经济建设为中心",
            "从封闭半封闭转向对外开放",
            "从“两个凡是”转到实事求是、一切从实际出发",
            "从僵化半僵化到全面改革"
        ],
        "难度": "中",
        "题型": "多选题",
        "正确答案": "A.B.D.",
        "解析": ""
    },
    {
        "题号": 142,
        "题目": "邓小平理论是与马克思列宁主义、毛泽东思想一脉相承的、统一的科学体系，因此，邓小平理论是一个（）",
        "选项": [
            "绝对完整的科学体系",
            "开放的理论体系",
            "需要不断丰富和发展的理论体系",
            "指导社会主义国家革命和建设的理论体系"
        ],
        "难度": "中",
        "题型": "多选题",
        "正确答案": "B.C.",
        "解析": ""
    },
    {
        "题号": 143,
        "题目": "“三个代表”重要思想的核心观点是：我们党必须始终代表______？",
        "选项": [
            "中国先进生产力的发展要求",
            "中国先进文化的前进方向",
            "中国最广大人民的根本利益",
            "社会全面进步的根本力量",
            "全心全意为人民服务"
        ],
        "难度": "易",
        "题型": "多选题",
        "正确答案": "A.B.C.",
        "解析": ""
    },
    {
        "题号": 144,
        "题目": "江泽民强调，（）是发展生产力的决定因素",
        "选项": [
            "科技进步",
            "人才",
            "创新",
            "教育",
            "文化"
        ],
        "难度": "难",
        "题型": "多选题",
        "正确答案": "A.C.",
        "解析": ""
    },
    {
        "题号": 145,
        "题目": "（）始终是推动我国先进生产力发展和社会全面进步的根本力量",
        "选项": [
            "中国共产党",
            "广大工人",
            "农民",
            "知识分子",
            "其他劳动群众"
        ],
        "难度": "难",
        "题型": "多选题",
        "正确答案": "B.C.D.",
        "解析": ""
    },
    {
        "题号": 146,
        "题目": "始终做到“三个代表”，是我们党的（）",
        "选项": [
            "立党之本",
            "时代要求",
            "执政之基",
            "力量之源",
            "历史经验"
        ],
        "难度": "易",
        "题型": "多选题",
        "正确答案": "A.C.D.",
        "解析": ""
    },
    {
        "题号": 147,
        "题目": "江泽民强调推进党的建设新的伟大工程，重点是加强党的执政能力建设，不断提高：",
        "选项": [
            "科学判断形势的能力",
            "驾驭市场经济的能力",
            "应对复杂局面的能力",
            "依法执政的能力",
            "总揽全局的能力"
        ],
        "难度": "中",
        "题型": "多选题",
        "正确答案": "A.B.C.D.E.",
        "解析": ""
    },
    {
        "题号": 148,
        "题目": "生产力最革命、最活跃的因素是：",
        "选项": [
            "生产资料",
            "科学技术",
            "人",
            "劳动对象"
        ],
        "难度": "中",
        "题型": "单选题",
        "正确答案": "C",
        "解析": ""
    },
    {
        "题号": 149,
        "题目": "我们全部工作的出发点和落脚点，就是：",
        "选项": [
            "构建人类命运共同体",
            "建设社会主义精神文明",
            "不断实现好维护好发展好最广大人民的根本利益",
            "建立和谐世界"
        ],
        "难度": "易",
        "题型": "单选题",
        "正确答案": "C",
        "解析": ""
    },
    {
        "题号": 150,
        "题目": "党要承担起推动中国社会进步的历史责任，必须始终紧紧抓住：",
        "选项": [
            "A.战略机遇期",
            "B.科教兴国战略",
            "C.发展这个执政兴国的第一要务",
            "D.社会主义政治文明建设"
        ],
        "难度": "易",
        "题型": "单选题",
        "正确答案": "C",
        "解析": "试题解析"
    },
    {
        "题号": 151,
        "题目": "明确提出使用“社会主义市场经体制”这个提法的是：",
        "选项": [
            "A.邓小平",
            "B.江泽民",
            "C.胡锦涛",
            "D.习近平"
        ],
        "难度": "中",
        "题型": "单选题",
        "正确答案": "B",
        "解析": "试题解析"
    },
    {
        "题号": 152,
        "题目": "社会主义(初级阶段)基本经济制度是：",
        "选项": [
            "A.公有制为主体、多种所有制经济共同发展",
            "B.各类市场主体自由竞争",
            "C.建立健全社会主义分配制度",
            "D.国家保护一切财产安全和利益"
        ],
        "难度": "易",
        "题型": "单选题",
        "正确答案": "A",
        "解析": "试题解析"
    },
    {
        "题号": 153,
        "题目": "江泽民在（ ）把社会主义物质文明、政治文明、精神文明一起确立为社会主义现代化全面发展的三大基本目标。",
        "选项": [
            "A.党十五大报告中",
            "B.党十六大报告中",
            "C.建党八十周年讲话中",
            "D.党十四届三中全会的讲话中"
        ],
        "难度": "难",
        "题型": "单选题",
        "正确答案": "B",
        "解析": "试题解析"
    },
    {
        "题号": 154,
        "题目": "坚持党的领导，核心是：",
        "选项": [
            "A.坚持党要管党",
            "B.坚持党的先进性",
            "C.坚持党的优良传统",
            "D.坚持党的阶级基础"
        ],
        "难度": "难",
        "题型": "单选题",
        "正确答案": "B",
        "解析": "试题解析"
    },
    {
        "题号": 155,
        "题目": "江泽民强调推进党的建设新的伟大工程，重点是加强：",
        "选项": [
            "A.党的群众基础",
            "B.党的执政能力建设",
            "C.党的阶级基础",
            "D.党的组织建设"
        ],
        "难度": "难",
        "题型": "单选题",
        "正确答案": "B",
        "解析": "试题解析"
    },
    {
        "题号": 156,
        "题目": "江泽民强调，我们党执政后最大的危险是:",
        "选项": [
            "A.能力不足",
            "B.精神懈怠",
            "C.脱离群众",
            "D.消极腐败"
        ],
        "难度": "难",
        "题型": "单选题",
        "正确答案": "C",
        "解析": "试题解析"
    },
    {
        "题号": 157,
        "题目": "我们党的立党之本、执政之基、力量之源是：",
        "选项": [
            "A.始终进行理论创新",
            "B.始终与时代同进步，与世界同发展",
            "C.始终做到“三个代表”",
            "D.始终做到独立自主、自力更生"
        ],
        "难度": "易",
        "题型": "单选题",
        "正确答案": "C",
        "解析": "试题解析"
    },
    {
        "题号": 158,
        "题目": "“三个代表”重要思想在邓小平理论的基础上，创造性地回答了：",
        "选项": [
            "A.什么是社会主义、怎样建设社会主义的问题",
            "B.进行什么样的革命，怎样进行革命的问题",
            "C.实现什么样的发展，怎样发展的问题",
            "D.建设什么样的党、怎样建设党的问题"
        ],
        "难度": "中",
        "题型": "单选题",
        "正确答案": "D",
        "解析": "试题解析"
    },
    {
        "题号": 159,
        "题目": "科学发展观对新形势下对（）等重大问题作出了新的科学回答",
        "选项": [
            "A.什么是马克思主义、怎样对待马克思主义",
            "B.什么是社会主义、怎样建设社会主义",
            "C.建设什么样的党、怎样建设党",
            "D.实现什么样的发展、怎样发展"
        ],
        "难度": "中",
        "题型": "单选题",
        "正确答案": "D",
        "解析": "试题解析"
    },
    {
        "题号": 160,
        "题目": "科学发展观的第一要义是：（）",
        "选项": [
            "A.科教兴国",
            "B.发展",
            "C.发展战略",
            "D.发展道路"
        ],
        "难度": "易",
        "题型": "单选题",
        "正确答案": "B",
        "解析": "试题解析"
    },
    {
        "题号": 161,
        "题目": "科学发展观的核心立场是：（）",
        "选项": [
            "A.发展",
            "B.以人为本",
            "C.全面协调可持续",
            "D.统筹兼顾"
        ],
        "难度": "易",
        "题型": "单选题",
        "正确答案": "B",
        "解析": "试题解析"
    },
    {
        "题号": 162,
        "题目": "科学发展观的基本要求是：（）",
        "选项": [
            "A.更快更好",
            "B.高质量",
            "C.全面协调可持续",
            "D.以人为本"
        ],
        "难度": "易",
        "题型": "单选题",
        "正确答案": "C",
        "解析": "试题解析"
    },
    {
        "题号": 163,
        "题目": "科学发展观的根本方法是：（）",
        "选项": [
            "A.发展",
            "B.以人为本",
            "C.全面协调可持续",
            "D.统筹兼顾"
        ],
        "难度": "易",
        "题型": "单选题",
        "正确答案": "D",
        "解析": "试题解析"
    },
    {
        "题号": 164,
        "题目": "（）是解决中国一切问题的“总钥匙”",
        "选项": [
            "A.改革",
            "B.开放",
            "C.发展",
            "D.建设"
        ],
        "难度": "易",
        "题型": "单选题",
        "正确答案": "C",
        "解析": "试题解析"
    },
    {
        "题号": 165,
        "题目": "党的十七大报告指出，科学发展观是发展中国特色社会主义必须坚持和贯彻的（）",
        "选项": [
            "A.重大战略思想",
            "B.行动指南",
            "C.重大指导方针",
            "D.指导思想"
        ],
        "难度": "易",
        "题型": "单选题",
        "正确答案": "A",
        "解析": "试题解析"
    },
    {
        "题号": 166,
        "题目": "中国共产党在党的文件中第一次提出科学发展观是在（）上",
        "选项": [
            "A.党的十六大",
            "B.党的十六届三中全会",
            "C.党的十六届四中全会",
            "D.党的十七大"
        ],
        "难度": "易",
        "题型": "单选题",
        "正确答案": "B",
        "解析": "试题解析"
    },
    {
        "题号": 167,
        "题目": "（）对科学发展观的理论定位、理论依据、理论内涵作了全面阐述。",
        "选项": [
            "A.党的十六大",
            "B.党的十六届三中全会",
            "C.党的十七大",
            "D.党的十七届五中全会"
        ],
        "难度": "易",
        "题型": "单选题",
        "正确答案": "C",
        "解析": "试题解析"
    },
    {
        "题号": 168,
        "题目": "（）关于《中国共产党章程（修正案）》的决议，将科学发展观写入党章",
        "选项": [
            "A.党的十六大",
            "B.党的十六届三中全会",
            "C.党的十七大",
            "D.党的十八大"
        ],
        "难度": "易",
        "题型": "单选题",
        "正确答案": "C",
        "解析": "试题解析"
    },
    {
        "题号": 169,
        "题目": "（）把科学发展观确立为党必须长期坚持的指导思想",
        "选项": [
            "A.党的十六大",
            "B.党的十七大",
            "C.党的十八大",
            "D.党的十九大"
        ],
        "难度": "易",
        "题型": "单选题",
        "正确答案": "C",
        "解析": "试题解析"
    },
    {
        "题号": 170,
        "题目": "科学发展观坚持以人为本，始终把实现好、维护好、发展好（）的根本利益作为党和国家一切工作的出发点和落脚点",
        "选项": [
            "A.全体党员",
            "B.最广大人民",
            "C.统治阶级",
            "D.工人、农民、知识分子"
        ],
        "难度": "易",
        "题型": "单选题",
        "正确答案": "B",
        "解析": "试题解析"
    },
    {
        "题号": 171,
        "题目": "科学发展观强调，（）是党执政后的一项根本建设",
        "选项": [
            "A.执政能力建设",
            "B.政治建设",
            "C.纪律建设",
            "D.思想建设"
        ],
        "难度": "中",
        "题型": "单选题",
        "正确答案": "A",
        "解析": "试题解析"
    },
    {
        "题号": 172,
        "题目": "科学发展观是以（）为主要代表的中国共产党人，在新世纪新阶段全面建设小康社会进程中，在新的历史起点上推进中国特色社会主义事业过程中形成和发展起来的",
        "选项": [
            "A.邓小平",
            "B.江泽民",
            "C.胡锦涛",
            "D.习近平"
        ],
        "难度": "易",
        "题型": "单选题",
        "正确答案": "C",
        "解析": "试题解析"
    },
    {
        "题号": 178,
        "题目": "对个体农业和手工业实行社会主义改造的方针是",
        "选项": [
            "A.趁热打铁，积极领导",
            "B.自愿互利，国家帮助",
            "C.积极领导，稳步前进",
            "D.国家帮助，典型示范"
        ],
        "难度": "易",
        "题型": "单选题",
        "正确答案": "C",
        "解析": "试题解析"
    },
    {
        "题号": 179,
        "题目": "我国社会主义改造基本完成是在",
        "选项": [
            "A.A.1949年",
            "B.B.1952年",
            "C.C.1956年",
            "D.D.1978年"
        ],
        "难度": "易",
        "题型": "单选题",
        "正确答案": "C",
        "解析": "试题解析"
    },
    {
        "题号": 180,
        "题目": "（）是无产阶级政党的根本政治原则，是指导党内生活的基本准则。",
        "选项": [
            "A.党内民主",
            "B.民主集中制",
            "C.民主制度",
            "D.代表制度"
        ],
        "难度": "易",
        "题型": "单选题",
        "正确答案": "B",
        "解析": "试题解析"
    },
    {
        "题号": 181,
        "题目": "1.在探索适合中国国情的社会主义道路问题上，第一次提出社会主义本质概念的是（）",
        "选项": [
            "A.刘少奇",
            "B.周恩来",
            "C.邓小平",
            "D.陈云"
        ],
        "难度": "易",
        "题型": "单选题",
        "正确答案": "C",
        "解析": "试题解析"
    },
    {
        "题号": 182,
        "题目": "2.邓小平社会主义本质理论中一个十分明显和突出的特点和创造是（）",
        "选项": [
            "A.强调解放生产力，发展生产力",
            "B.强调消灭剥削",
            "C.强调消除两极分化",
            "D.强调最终达到共同富裕"
        ],
        "难度": "易",
        "题型": "单选题",
        "正确答案": "A",
        "解析": "试题解析"
    },
    {
        "题号": 183,
        "题目": "3.在社会主义本质中，明确提出社会主义的根本目标是（）",
        "选项": [
            "A.解放生产力和发展生产力",
            "B.消灭剥削",
            "C.消除两极分化",
            "D.实现共同富裕"
        ],
        "难度": "易",
        "题型": "单选题",
        "正确答案": "D",
        "解析": "试题解析"
    },
    {
        "题号": 184,
        "题目": "4.邓小平指出\"发展才是硬道理\"，硬就硬在（）",
        "选项": [
            "A.实现国家统一要靠经济发展",
            "B.维护世界和平",
            "C.提高人民群众的生活水平要靠经济发展",
            "D.解决社会主义初级阶段的各种社会矛盾和问题，都要依靠发展"
        ],
        "难度": "易",
        "题型": "单选题",
        "正确答案": "D",
        "解析": "试题解析"
    },
    {
        "题号": 185,
        "题目": "5.明确提出\"科学技术是第一生产力\"的是（）",
        "选项": [
            "A.毛泽东",
            "B.刘少奇",
            "C.周恩来",
            "D.邓小平"
        ],
        "难度": "易",
        "题型": "单选题",
        "正确答案": "D",
        "解析": "试题解析"
    },
    {
        "题号": 186,
        "题目": "6.邓小平关于建设有中国特色社会主义的首要的基本的理论问题是（）",
        "选项": [
            "A.什么是市场经济，怎样建立市场经济体制",
            "B.解放思想.实事求是",
            "C.什么是社会主义，怎样建设社会主义",
            "D.一个中心，两个基本点"
        ],
        "难度": "易",
        "题型": "单选题",
        "正确答案": "C",
        "解析": "试题解析"
    },
    {
        "题号": 187,
        "题目": "7.体现社会主义本质的前提是（）",
        "选项": [
            "A.坚持公有制和按劳分配，维护公有制和按劳分配的主体地位",
            "B.坚持三个有利于的标准",
            "C.坚持社会主义市场经济的改革目标",
            "D.坚持马克思列宁主义.毛泽东思想"
        ],
        "难度": "易",
        "题型": "单选题",
        "正确答案": "A",
        "解析": "试题解析"
    },
    {
        "题号": 188,
        "题目": "8.马克思主义认为，共产主义的最终目的是（）",
        "选项": [
            "A.实现人的自由而全面的发展",
            "B.生产力发展的成果为全体人民所享有",
            "C.消灭剥削，消除两极分化",
            "D.实现共同富裕"
        ],
        "难度": "易",
        "题型": "单选题",
        "正确答案": "A",
        "解析": "试题解析"
    },
    {
        "题号": 189,
        "题目": "9.社会主义本质理论的重要意义是（）",
        "选项": [
            "A.社会主义生产力的发展和社会主义社会由低级到高级.由不完善到逐步完善的过程体现",
            "B.把我们对社会主义的认识提高到了一个新的科学水平",
            "C.是一个随着生产力的发展而逐步实现的比较长的动态过程",
            "D.是走向人的自由而全面发展所必经阶段的理论"
        ],
        "难度": "易",
        "题型": "单选题",
        "正确答案": "B",
        "解析": "试题解析"
    },
    {
        "题号": 190,
        "题目": "10.第一次提出我国社会主义制度还处在初级的阶段的是（）",
        "选项": [
            "A.十一届三中全会",
            "B.十一届六中全会",
            "C.十三大",
            "D.十二届三中全会"
        ],
        "难度": "易",
        "题型": "单选题",
        "正确答案": "B",
        "解析": "试题解析"
    },
    {
        "题号": 191,
        "题目": "11.我国社会主义初级阶段的主要矛盾是（）",
        "选项": [
            "A.生产力与生产关系之间的矛盾",
            "B.经济基础与上层建筑之间的矛盾",
            "C.人民日益增长的物质文化需要同落后的社会生产之间的矛盾",
            "D.社会主义与资本主义之间的矛盾"
        ],
        "难度": "易",
        "题型": "单选题",
        "正确答案": "C",
        "解析": "试题解析"
    },
    {
        "题号": 192,
        "题目": "12.在我党的历史文献中第一次使用了\"社会主义初级阶段\"这一概念是（）",
        "选项": [
            "A.1981年《关于建国以来党的若干历史问题的决议》",
            "B.1982年党的十二大报告",
            "C.1986年《中共中央关于社会主义精神文明建设指导方针的决议》",
            "D.1987年十三大报告"
        ],
        "难度": "易",
        "题型": "单选题",
        "正确答案": "A",
        "解析": "试题解析"
    },
    {
        "题号": 193,
        "题目": "13.下列不属于社会主义初级阶段特征的是（）",
        "选项": [
            "A.是由一党专政转变为多党执政的历史阶段",
            "B.是由农业国逐步转变为工业国的历史阶段",
            "C.是科技教育文化由比较落后转变为比较发达的历史阶段",
            "D.是由人民生活水平比较低转变为比较富裕的历史阶段"
        ],
        "难度": "易",
        "题型": "单选题",
        "正确答案": "A",
        "解析": "试题解析"
    },
    {
        "题号": 194,
        "题目": "14.党的十三大在科学阐述社会主义初级阶段理论的同时，正式提出了党在社会主义初级阶段的（）",
        "选项": [
            "A.发展战略",
            "B.基本纲领",
            "C.基本路线",
            "D.基本目标"
        ],
        "难度": "易",
        "题型": "单选题",
        "正确答案": "C",
        "解析": "试题解析"
    },
    {
        "题号": 195,
        "题目": "15.坚持党的社会主义初级阶段的基本路线100年不动摇，关键是坚持（）",
        "选项": [
            "A.以经济建设为中心不动摇",
            "B.自力更生.艰苦创业的方针不动摇",
            "C.两手抓.两手都要硬的方针不动摇",
            "D.改革开放不动摇"
        ],
        "难度": "易",
        "题型": "单选题",
        "正确答案": "A",
        "解析": "试题解析"
    },
    {
        "题号": 196,
        "题目": "16.进入20世纪90年代以来，我国对外开放基本形成了（）",
        "选项": [
            "A.全方位、多形式、多层次的开放格局",
            "B.全方位、多渠道、多层次的开放格局",
            "C.全方位、多层次、宽领域的开放格局",
            "D.全方位、多形式、宽领域的开放格局"
        ],
        "难度": "易",
        "题型": "单选题",
        "正确答案": "C",
        "解析": "试题解析"
    },
    {
        "题号": 197,
        "题目": "17.1992年，在南方谈话中，提出了（）作为判断改革成败得失的标准。",
        "选项": [
            "A.解放生产力标准",
            "B.姓\"资\"姓\"社\"标准",
            "C.\"三个有利于\"标准",
            "D.提高综合国力的标准"
        ],
        "难度": "易",
        "题型": "单选题",
        "正确答案": "C",
        "解析": "试题解析"
    },
    {
        "题号": 198,
        "题目": "18.市场经济可以在不同的社会制度下存在，它可以为资本主义所利用，也可以为社会主义所利用，社会主义市场经济是同社会主义基本制度结合在一起的，它的基本特征有（）",
        "选项": [
            "A.①坚持公有制的主体地位是社会主义市场经济的基本特征",
            "B.②实现共同富裕是社会主义市场经济的根本目标",
            "C.③在社会主义市场经济条件下，国家能实行强有力的宏观调控",
            "D.④能运用各种手段对国民经济进行控制和调节",
            "E.⑤能加强和完善宏观调控，有效地指挥企业的生产和经营",
            "F.①②③",
            "G.③④⑤",
            "H.①③⑤",
            "I.②③④"
        ],
        "难度": "易",
        "题型": "单选题",
        "正确答案": "I",
        "解析": "试题解析"
    },
    {
        "题号": 199,
        "题目": "19.中国的社会主义市场经济体制，必须与我国的国情相结合，既有一般市场经济的共性，又有我国的显著特点。这里讲的国情和特点是指（）",
        "选项": [
            "A.社会主义市场经济体制重视.遵循价值规律的作用",
            "B.社会主义市场经济体制下的市场对资源配置的基础性作用",
            "C.社会主义市场经济体制下的各企业有独立的物质利益",
            "D.社会主义市场经济体制是同社会主义基本制度结合在一起的"
        ],
        "难度": "易",
        "题型": "单选题",
        "正确答案": "D",
        "解析": "试题解析"
    },
    {
        "题号": 200,
        "题目": "20.国家宏观调控正确理解的有（）",
        "选项": [
            "A.①宏观调控是指国家运用各种手段对国民经济进行的机制和调节",
            "B.②宏观调控的主要任务是控制通货膨胀",
            "C.③国家宏观调控的手段相互联系.相互补充，共同构成宏观调控体系",
            "D.④在市场经济条件下，宏观调控以经济手段和行政手段为主",
            "E.①②③",
            "F.②③④",
            "G.①②③",
            "H.①③④"
        ],
        "难度": "易",
        "题型": "单选题",
        "正确答案": "G",
        "解析": "试题解析"
    },
    {
        "题号": 201,
        "题目": "21.我国正处在并将长期处于社会主义初级阶段，这是搞清什么是社会主义的重要容之一。社会主义初级阶段（）",
        "选项": [
            "A.不是社会主义社会形态",
            "B.具有落后性.多层次性和不平衡性的特点",
            "C.具有同发达资本主义国家相当的生产力发展水平",
            "D.多种经济成分并存的过渡时期"
        ],
        "难度": "易",
        "题型": "单选题",
        "正确答案": "B",
        "解析": "试题解析"
    },
    {
        "题号": 202,
        "题目": "22.坚持党的基本路线一百年不动摇的关键是（）",
        "选项": [
            "A.坚持以经济建设为中心不动摇",
            "B.坚持两手抓、两手都要硬的方针不动摇",
            "C.坚持四项基本原则不动摇",
            "D.坚持改革开放不动摇"
        ],
        "难度": "易",
        "题型": "单选题",
        "正确答案": "A",
        "解析": "试题解析"
    },
    {
        "题号": 203,
        "题目": "23.四项基本原则是党在社会主义初级阶段基本路线的重要组成部分。坚持四项基本原则的核心是（）",
        "选项": [
            "A.坚持社会主义道路",
            "B.坚持人民专政",
            "C.坚持共产党的领导",
            "D.坚持马列主义、毛泽东思想"
        ],
        "难度": "易",
        "题型": "单选题",
        "正确答案": "C",
        "解析": "试题解析"
    },
    {
        "题号": 204,
        "题目": "24.改革开放是（）",
        "选项": [
            "A.彻底改变我国的基本制度",
            "B.社会主义制度的自我完善和发展",
            "C.对原有制度的修修补补",
            "D.对社会主义制度的根本性变革"
        ],
        "难度": "易",
        "题型": "单选题",
        "正确答案": "B",
        "解析": "试题解析"
    },
    {
        "题号": 205,
        "题目": "25.中国的改革是从（）开始起步的。",
        "选项": [
            "A.沿海",
            "B.城市",
            "C.内地",
            "D.农村"
        ],
        "难度": "易",
        "题型": "单选题",
        "正确答案": "D",
        "解析": "试题解析"
    },
    {
        "题号": 206,
        "题目": "26.按劳分配主体以外的分配方式主要是按（）分配。",
        "选项": [
            "A.资本",
            "B.技术",
            "C.生产要素",
            "D.管理"
        ],
        "难度": "易",
        "题型": "单选题",
        "正确答案": "C",
        "解析": "试题解析"
    },
    {
        "题号": 207,
        "题目": "27.建设资源节约型社会是统筹（）的重大举措。",
        "选项": [
            "A.经济社会发展",
            "B.人与自然和谐发展",
            "C.城乡发展",
            "D.区域发展"
        ],
        "难度": "易",
        "题型": "单选题",
        "正确答案": "B",
        "解析": "试题解析"
    },
    {
        "题号": 208,
        "题目": "28.我国实行\"一国两制\"不会改变人民专政国家的社会主义性质。这是因为（）。",
        "选项": [
            "A.特别行政区只是中华人民国的一个行政区域",
            "B.特别行政区政府是在中华人民国中央人民政府的统一领导下",
            "C.特别行政区享有地一般地方行政区域所没有的高度自治权",
            "D.两种制度地位不同，社会主义制度是主体"
        ],
        "难度": "易",
        "题型": "单选题",
        "正确答案": "D",
        "解析": "试题解析"
    },
    {
        "题号": 209,
        "题目": "29.我们过去对什么是社会主义的问题之所以没有完全搞清楚，一个重要的原因就是（）",
        "选项": [
            "A.离开了阶级斗争谈社会主义",
            "B.离开了思想道德建设谈社会主义",
            "C.离开了生产力水平谈社会主义",
            "D.离开了生产关系变革谈社会主义"
        ],
        "难度": "易",
        "题型": "单选题",
        "正确答案": "C",
        "解析": "试题解析"
    },
    {
        "题号": 210,
        "题目": "30.在社会主义本质中，明确提出社会主义的根本目标是（）",
        "选项": [
            "A.解放生产力和发展生产力",
            "B.消灭剥削",
            "C.消除两极分化",
            "D.实现共同富裕"
        ],
        "难度": "易",
        "题型": "单选题",
        "正确答案": "D",
        "解析": "试题解析"
    },
    {
        "题号": 211,
        "题目": "31.（）是我们的立国之本。",
        "选项": [
            "A.坚持四项基本原则",
            "B.坚持改革开放",
            "C.坚持党的领导",
            "D.坚持大力发展生产力"
        ],
        "难度": "易",
        "题型": "单选题",
        "正确答案": "A",
        "解析": "试题解析"
    },
    {
        "题号": 212,
        "题目": "32.（）是我们的强国之路。",
        "选项": [
            "A.坚持四项基本原则",
            "B.坚持改革开放",
            "C.坚持党的领导",
            "D.坚持大力发展生产力"
        ],
        "难度": "易",
        "题型": "单选题",
        "正确答案": "B",
        "解析": "试题解析"
    },
    {
        "题号": 213,
        "题目": "33.无产阶级政党的最高纲领是（）",
        "选项": [
            "A.建设有中国特色社会主义",
            "B.基本实现现代化",
            "C.发展社会主义民主政治",
            "D.实现共产主义"
        ],
        "难度": "易",
        "题型": "单选题",
        "正确答案": "D",
        "解析": "试题解析"
    },
    {
        "题号": 214,
        "题目": "34.邓小平指出\"发展才是硬道理\"，硬就硬在（）",
        "选项": [
            "A.实现国家统一要靠经济发展",
            "B.维护世界和平",
            "C.提高人民群众的生活水平要靠经济发展",
            "D.解决社会主义初级阶段的各种社会矛盾和问题，都要依靠发展"
        ],
        "难度": "易",
        "题型": "单选题",
        "正确答案": "D",
        "解析": "试题解析"
    },
    {
        "题号": 215,
        "题目": "35.对社会主义初级阶段的特征进行全面概括的是（）",
        "选项": [
            "A.十二大",
            "B.十三大",
            "C.十四大",
            "D.十五大"
        ],
        "难度": "易",
        "题型": "单选题",
        "正确答案": "D",
        "解析": "试题解析"
    },
    {
        "题号": 216,
        "题目": "36.社会主义初级阶段在各方面先进和落后的并存，是我国基本国情的重要特点，它决定了社会主义初级阶段的发展具有的总的基本特征是（）",
        "选项": [
            "A.逐步摆脱不发达状态，基本实现社会主义现代化的历史阶段",
            "B.由农业国逐步转变为工业国的历史阶段",
            "C.由经济文化发展不平衡逐步变为缩小差距的历史阶段",
            "D.由自然经济半自然经济占很大比重，逐步转变为经济市场化程度较高的历史阶段"
        ],
        "难度": "易",
        "题型": "单选题",
        "正确答案": "A",
        "解析": "试题解析"
    },{
        "题号": 217,
        "题目": "'三步走'的发展战略是我国社会主义现代化建设的科学的行动纲领，这一发展战略（）",
        "选项": [
            "A.坚持了雄心壮志和实事求是的统一",
            "B.坚持了经济发展和实现社会主义本质要求的统一",
            "C.坚持了经济与社会的全面协调发展",
            "D.是对中国国情和时代特征的深刻把握",
            "E.是对现代化客观规律的正确反映"
        ],
        "难度": "易",
        "题型": "多选题",
        "正确答案": "A.B.C.D.E.",
        "解析": "试题解析"
    },
    {
        "题号": 218,
        "题目": "非公有制经济主要包括（）。",
        "选项": [
            "A.个体经济",
            "B.私营经济",
            "C.外商独资经济",
            "D.混合所有制经济中的非公有制成分"
        ],
        "难度": "易",
        "题型": "多选题",
        "正确答案": "A.B.C.D.",
        "解析": "试题解析"
    },
    {
        "题号": 219,
        "题目": "改革开放的目的就是（）",
        "选项": [
            "A.要解放和发展社会生产力，实现国家现代化，让中国人民富裕起来，振兴伟大的中华民族",
            "B.要推动我国社会主义制度自我完善和发展，赋予社会主义新的生机活力，建设和发展中国特色社会主义",
            "C.要在引领当代中国发展进步中加强和改进党的建设，保持和发展党的先进性，确保党始终走在时代前列",
            "D.要让中国进入发达国家的行列"
        ],
        "难度": "易",
        "题型": "多选题",
        "正确答案": "A.B.C.",
        "解析": "试题解析"
    },
    {
        "题号": 220,
        "题目": "下面关于改革开放正确的论述是（）",
        "选项": [
            "A.改革开放是决定当代中国命运的关键抉择",
            "B.改革开放是发展中国特色社会主义的必由之路",
            "C.改革开放是发展中国特色社会主义的强大动力",
            "D.新时期最鲜明的特点是改革开放"
        ],
        "难度": "易",
        "题型": "多选题",
        "正确答案": "A.B.C.D.",
        "解析": "试题解析"
    },
    {
        "题号": 221,
        "题目": "坚持以经济建设为中心，从根本上说是由（）决定的。",
        "选项": [
            "A.当前的国际环境",
            "B.社会主义初级阶段的主要矛盾",
            "C.实现社会主义现代化的历史任务",
            "D.实现社会主义建设发展战略的目标"
        ],
        "难度": "易",
        "题型": "单选题",
        "正确答案": "B",
        "解析": "试题解析"
    },
    {
        "题号": 222,
        "题目": "党的十三大系统地阐述了社会主义初级阶段的科学内涵，阐明了社会主义初级阶段这个论断，包括两层含义（）",
        "选项": [
            "A.我国社会已经是社会主义社会。我们必须坚持而不能离开社会主义。",
            "B.我国的社会主义社会还处在初级阶段。",
            "C.社会主义初级阶段是任何社会主义国家都不可逾越的必经阶段。",
            "D.社会主义初级阶段和共产主义的初级阶段是同一个阶段。"
        ],
        "难度": "中",
        "题型": "多选题",
        "正确答案": "A.B.",
        "解析": "试题解析"
    },
    {
        "题号": 223,
        "题目": "下列属于邓小平“两手抓，两手都要硬”理论的有（）",
        "选项": [
            "A.一手抓物质文明，一手抓精神文明",
            "B.一手抓建设，一手抓法制",
            "C.一手抓市场经济，一手抓计划经济",
            "D.一手抓改革开放，一手抓惩治腐败"
        ],
        "难度": "易",
        "题型": "多选题",
        "正确答案": "A.B.D.",
        "解析": "试题解析"
    },
    {
        "题号": 224,
        "题目": "邓小平理论的精髓中，解放思想通常包括两种情况（）",
        "选项": [
            "A.A．对原先的认识进行再认识，这其中既有对原先认识中那些正确部分的坚持，也有对原先认识中那些错误部分的纠正",
            "B.B．解放思想、实事求是，一切从社会主义初级阶段的实际出发",
            "C.C．解放思想、实事求是，破除了僵化的社会主义模式观念，坚持走自己的路。",
            "D.D．在研究新情况、解决新问题、总结新经验的基础上，形成新的正确认识"
        ],
        "难度": "中",
        "题型": "多选题",
        "正确答案": "A.D.",
        "解析": "试题解析"
    },
    {
        "题号": 225,
        "题目": "邓小平理论中分三步走基本实现现代化的发展战略，第三步战略目标是（）",
        "选项": [
            "A.到21世纪中叶，人均国民生产总值达到中等发达国家水平，人民生活比较富裕，基本实现现代化。然后，在这个基础上继续前进",
            "B.把我国建设成为富强、民主、文明的社会主义现代化国家",
            "C.把我国建设成为富强、民主、文明、和谐的社会主义现代化国家",
            "D.把我国建设成为富强、民主、文明、和谐、美丽的社会主义现代化强国"
        ],
        "难度": "易",
        "题型": "单选题",
        "正确答案": "A",
        "解析": "试题解析"
    }

]
